openai_proxy/__init__.py
openai_proxy/chat_completion.py
openai_proxy/completion.py
openai_proxy/embeddings.py
openai_proxy/image.py
openai_proxy/price.py
openai_proxy/utils/__init__.py
openai_proxy/utils/auth.py
openai_proxy/utils/constants.py
openai_proxy/utils/token_estimator.py
openai_proxy/utils/constants/__init__.py
openai_proxy-0.2.5.dist-info/METADATA
openai_proxy-0.2.5.dist-info/WHEEL
openai_proxy-0.2.5.dist-info/top_level.txt
openai_proxy-0.2.5.dist-info/RECORD
