Metadata-Version: 2.1
Name: openai-proxy
Version: 0.2.5
Summary: A price proxy for the OpenAI API
Home-page: UNKNOWN
Author: Ayotomiwa Akinyele
Author-email: <ayotomiwa.akinyele@gmail.com>
License: UNKNOWN
Keywords: python,openai,proxy,api,wrapper
Platform: UNKNOWN
Classifier: Development Status :: 3 - Alpha
Classifier: Intended Audience :: Education
Classifier: Programming Language :: Python :: 2
Classifier: Programming Language :: Python :: 3
Classifier: Operating System :: MacOS :: MacOS X
Classifier: Operating System :: Microsoft :: Windows
Requires-Dist: openai
Requires-Dist: tiktoken
